waves/__init__.py
waves/authentication/__init__.py
waves/authentication/admin.py
waves/authentication/apps.py
waves/authentication/auth.py
waves/authentication/models.py
waves/authentication/serializers.py
waves/authentication/signals.py
waves/authentication/tests.py
waves/authentication/views.py
waves/authentication/migrations/0001_initial.py
waves/authentication/migrations/0002_auto_20180313_1344.py
waves/authentication/migrations/__init__.py
waves/wcore/__init__.py
waves/wcore/apps.py
waves/wcore/mails.py
waves/wcore/settings.py
waves/wcore/signals.py
waves/wcore/tasks.py
waves/wcore/urls.py
waves/wcore/adaptors/__init__.py
waves/wcore/adaptors/api.py
waves/wcore/adaptors/cluster.py
waves/wcore/adaptors/const.py
waves/wcore/adaptors/exceptions.py
waves/wcore/adaptors/importer.py
waves/wcore/adaptors/loader.py
waves/wcore/adaptors/mocks.py
waves/wcore/adaptors/saga_python.py
waves/wcore/adaptors/shell.py
waves/wcore/adaptors/tests.py
waves/wcore/adaptors/utils.py
waves/wcore/admin/__init__.py
waves/wcore/admin/adaptors.py
waves/wcore/admin/base.py
waves/wcore/admin/binaries.py
waves/wcore/admin/inputs.py
waves/wcore/admin/jobs.py
waves/wcore/admin/runners.py
waves/wcore/admin/services.py
waves/wcore/admin/submissions.py
waves/wcore/admin/forms/__init__.py
waves/wcore/admin/forms/adaptors.py
waves/wcore/admin/forms/jobs.py
waves/wcore/admin/forms/runners.py
waves/wcore/admin/forms/services.py
waves/wcore/admin/views/__init__.py
waves/wcore/admin/views/export.py
waves/wcore/admin/views/job_tool.py
waves/wcore/admin/views/json_view.py
waves/wcore/admin/views/runner_tool.py
waves/wcore/admin/views/service_tool.py
waves/wcore/api/__init__.py
waves/wcore/api/permissions.py
waves/wcore/api/share.py
waves/wcore/api/tests.py
waves/wcore/api/urls.py
waves/wcore/api/v1/__init__.py
waves/wcore/api/v1/urls.py
waves/wcore/api/v1/serializers/__init__.py
waves/wcore/api/v1/serializers/fields.py
waves/wcore/api/v1/serializers/inputs.py
waves/wcore/api/v1/serializers/jobs.py
waves_core-1.6.6.dist-info/AUTHORS.md
waves_core-1.6.6.dist-info/LICENSE.md
waves_core-1.6.6.dist-info/METADATA
waves_core-1.6.6.dist-info/WHEEL
waves_core-1.6.6.dist-info/top_level.txt
waves_core-1.6.6.dist-info/RECORD
